{
  "accounts": {
    "AAPL": {
      "agent": {
        "cash": -7.105427357601002e-15,
        "sig": 1.0,
        "strategy": "buy_and_hold",
        "units": 0.17619282618605658
      },
      "agent_equity": 55.426736895739204,
      "hold": {
        "cash": 0.0,
        "units": 0.17619282618605658
      },
      "hold_equity": 55.42673689573921,
      "price": 314.5799865722656
    },
    "ADA/USD": {
      "agent": {
        "cash": -0.09999999999999432,
        "sig": 1.0,
        "strategy": "buy_and_hold",
        "units": 345.9882950400526
      },
      "agent_equity": 61.45131768762536,
      "hold": {
        "cash": 0.0,
        "units": 341.29692832764505
      },
      "hold_equity": 60.71672354948805,
      "price": 0.1779
    },
    "AMZN": {
      "agent": {
        "cash": 50.0,
        "sig": 0.0,
        "strategy": "rsi_reversion",
        "units": 0.0
      },
      "agent_equity": 50.0,
      "hold": {
        "cash": 0.0,
        "units": 0.2148781618264434
      },
      "hold_equity": 52.29704807452957,
      "price": 243.3800048828125
    },
    "AVAX/USD": {
      "agent": {
        "cash": 0.0,
        "sig": 1.0,
        "strategy": "macd",
        "units": 7.668711656441718
      },
      "agent_equity": 51.917177914110425,
      "hold": {
        "cash": 0.0,
        "units": 7.668711656441718
      },
      "hold_equity": 51.917177914110425,
      "price": 6.77
    },
    "BTC/USD": {
      "agent": {
        "cash": 0.0,
        "sig": 1.0,
        "strategy": "buy_and_hold",
        "units": 0.0008279822222281102
      },
      "agent_equity": 52.95833908090993,
      "hold": {
        "cash": 0.0,
        "units": 0.0008279822222281102
      },
      "hold_equity": 52.95833908090993,
      "price": 63960.72
    },
    "DOGE/USD": {
      "agent": {
        "cash": 100.0,
        "sig": -1.0,
        "strategy": "donchian_breakout",
        "units": -663.9224538573894
      },
      "agent_equity": 50.079670694462884,
      "hold": {
        "cash": 0.0,
        "units": 663.9224538573894
      },
      "hold_equity": 49.920329305537116,
      "price": 0.07519
    },
    "ETH/USD": {
      "agent": {
        "cash": 50.4269523544189,
        "sig": 0.0,
        "strategy": "ts_momentum",
        "units": 0.0
      },
      "agent_equity": 50.4269523544189,
      "hold": {
        "cash": 0.0,
        "units": 0.03149388073897242
      },
      "hold_equity": 56.58096131921568,
      "price": 1796.57
    },
    "GOOGL": {
      "agent": {
        "cash": 50.0,
        "sig": 0.0,
        "strategy": "rsi_reversion",
        "units": 0.0
      },
      "agent_equity": 50.0,
      "hold": {
        "cash": 0.0,
        "units": 0.1481964427788425
      },
      "hold_equity": 54.69634111087272,
      "price": 369.0799865722656
    },
    "LINK/USD": {
      "agent": {
        "cash": 0.0,
        "sig": 1.0,
        "strategy": "buy_and_hold",
        "units": 6.792555359326179
      },
      "agent_equity": 54.35402798532809,
      "hold": {
        "cash": 0.0,
        "units": 6.792555359326179
      },
      "hold_equity": 54.35402798532809,
      "price": 8.002
    },
    "LTC/USD": {
      "agent": {
        "cash": 50.0,
        "sig": 0.0,
        "strategy": "ts_momentum",
        "units": 0.0
      },
      "agent_equity": 50.0,
      "hold": {
        "cash": 0.0,
        "units": 1.1698642957416938
      },
      "hold_equity": 52.00046794571829,
      "price": 44.45
    },
    "META": {
      "agent": {
        "cash": -0.05000000000000426,
        "sig": 1.0,
        "strategy": "sma_timing",
        "units": 0.08877840716668894
      },
      "agent_equity": 53.75326392860274,
      "hold": {
        "cash": 0.0,
        "units": 0.09086778736937756
      },
      "hold_equity": 55.06951186073092,
      "price": 606.0399780273438
    },
    "MSFT": {
      "agent": {
        "cash": 0.0,
        "sig": 1.0,
        "strategy": "buy_and_hold",
        "units": 0.13405903916227502
      },
      "agent_equity": 52.762954833379034,
      "hold": {
        "cash": 0.0,
        "units": 0.13405903916227502
      },
      "hold_equity": 52.762954833379034,
      "price": 393.5799865722656
    },
    "NVDA": {
      "agent": {
        "cash": 50.0,
        "sig": 0.0,
        "strategy": "sma_timing",
        "units": 0.0
      },
      "agent_equity": 50.0,
      "hold": {
        "cash": 0.0,
        "units": 0.2596997886927562
      },
      "hold_equity": 50.37656390106364,
      "price": 193.97999572753906
    },
    "QQQ": {
      "agent": {
        "cash": -7.105427357601002e-15,
        "sig": 1.0,
        "strategy": "buy_and_hold",
        "units": 0.07076940301447249
      },
      "agent_equity": 50.13516765921215,
      "hold": {
        "cash": 0.0,
        "units": 0.07076940301447249
      },
      "hold_equity": 50.13516765921216,
      "price": 708.4299926757812
    },
    "SOL/USD": {
      "agent": {
        "cash": -0.056843489148583615,
        "sig": 1.0,
        "strategy": "buy_and_hold",
        "units": 0.6920317646527997
      },
      "agent_equity": 56.78664565943238,
      "hold": {
        "cash": 0.0,
        "units": 0.6956037840845855
      },
      "hold_equity": 57.13689482470785,
      "price": 82.14
    },
    "SPY": {
      "agent": {
        "cash": 0.0,
        "sig": 1.0,
        "strategy": "ts_momentum",
        "units": 0.06858804739407283
      },
      "agent_equity": 51.237917133716216,
      "hold": {
        "cash": 0.0,
        "units": 0.06858804739407283
      },
      "hold_equity": 51.237917133716216,
      "price": 747.03857421875
    },
    "TSLA": {
      "agent": {
        "cash": -0.09999999999999432,
        "sig": 1.0,
        "strategy": "macd",
        "units": 0.10837042524577649
      },
      "agent_equity": 43.87563578650047,
      "hold": {
        "cash": 0.0,
        "units": 0.1316794425355944
      },
      "hold_equity": 53.4342021117094,
      "price": 405.7900085449219
    },
    "XRP/USD": {
      "agent": {
        "cash": 0.0,
        "sig": 1.0,
        "strategy": "buy_and_hold",
        "units": 47.250047250047245
      },
      "agent_equity": 53.43507843507843,
      "hold": {
        "cash": 0.0,
        "units": 47.250047250047245
      },
      "hold_equity": 53.43507843507843,
      "price": 1.1309
    }
  },
  "created": "2026-06-27",
  "history": [
    {
      "agent_total": 900.0,
      "date": "2026-06-27",
      "hold_total": 900.0
    },
    {
      "agent_total": 900.0,
      "date": "2026-06-27",
      "hold_total": 900.0
    },
    {
      "agent_total": 898.5085747082028,
      "date": "2026-06-28",
      "hold_total": 895.3395369691184
    },
    {
      "agent_total": 894.9092255446823,
      "date": "2026-06-28",
      "hold_total": 889.7786061883053
    },
    {
      "agent_total": 898.4302273505317,
      "date": "2026-06-28",
      "hold_total": 895.1933624354183
    },
    {
      "agent_total": 900.4471955838201,
      "date": "2026-06-29",
      "hold_total": 906.1007685588108
    },
    {
      "agent_total": 897.1225912540275,
      "date": "2026-06-30",
      "hold_total": 904.0783962378573
    },
    {
      "agent_total": 918.1227055387701,
      "date": "2026-07-01",
      "hold_total": 932.9445534017232
    },
    {
      "agent_total": 922.6351563416667,
      "date": "2026-07-02",
      "hold_total": 941.4803215353227
    },
    {
      "agent_total": 927.4834103032986,
      "date": "2026-07-03",
      "hold_total": 950.0114219233841
    },
    {
      "agent_total": 935.4367119433759,
      "date": "2026-07-04",
      "hold_total": 961.6021020585499
    },
    {
      "agent_total": 936.1518884009236,
      "date": "2026-07-05",
      "hold_total": 961.9738377934298
    },
    {
      "agent_total": 941.4809265616133,
      "date": "2026-07-06",
      "hold_total": 969.4504560068004
    },
    {
      "agent_total": 938.6008860485163,
      "date": "2026-07-07",
      "hold_total": 964.4564439410467
    }
  ],
  "initial_capital": 900.0,
  "last_run": "2026-07-07",
  "symbols": [
    "BTC/USD",
    "ETH/USD",
    "SOL/USD",
    "XRP/USD",
    "DOGE/USD",
    "ADA/USD",
    "LTC/USD",
    "AVAX/USD",
    "LINK/USD",
    "AAPL",
    "MSFT",
    "NVDA",
    "TSLA",
    "AMZN",
    "GOOGL",
    "META",
    "SPY",
    "QQQ"
  ]
}