{
  "accounts": {
    "AAPL": {
      "agent": {
        "cash": -7.105427357601002e-15,
        "sig": 1.0,
        "strategy": "buy_and_hold",
        "units": 0.17619282618605658
      },
      "agent_equity": 49.413280254670894,
      "hold": {
        "cash": 0.0,
        "units": 0.17619282618605658
      },
      "hold_equity": 49.4132802546709,
      "price": 280.45001220703125
    },
    "ADA/USD": {
      "agent": {
        "cash": -0.09999999999999432,
        "sig": 1.0,
        "strategy": "buy_and_hold",
        "units": 345.9882950400526
      },
      "agent_equity": 50.10290161031164,
      "hold": {
        "cash": 0.0,
        "units": 341.29692832764505
      },
      "hold_equity": 49.5221843003413,
      "price": 0.1451
    },
    "AMZN": {
      "agent": {
        "cash": 50.0,
        "sig": 0.0,
        "strategy": "rsi_reversion",
        "units": 0.0
      },
      "agent_equity": 50.0,
      "hold": {
        "cash": 0.0,
        "units": 0.2148781618264434
      },
      "hold_equity": 51.536400497010675,
      "price": 239.84010314941406
    },
    "AVAX/USD": {
      "agent": {
        "cash": 0.0,
        "sig": 1.0,
        "strategy": "macd",
        "units": 7.668711656441718
      },
      "agent_equity": 51.15030674846626,
      "hold": {
        "cash": 0.0,
        "units": 7.668711656441718
      },
      "hold_equity": 51.15030674846626,
      "price": 6.67
    },
    "BTC/USD": {
      "agent": {
        "cash": 0.0,
        "sig": 1.0,
        "strategy": "buy_and_hold",
        "units": 0.0008279822222281102
      },
      "agent_equity": 49.460312907729495,
      "hold": {
        "cash": 0.0,
        "units": 0.0008279822222281102
      },
      "hold_equity": 49.460312907729495,
      "price": 59735.96
    },
    "DOGE/USD": {
      "agent": {
        "cash": 100.0,
        "sig": -1.0,
        "strategy": "momentum_roc",
        "units": -663.9224538573894
      },
      "agent_equity": 51.97184968795645,
      "hold": {
        "cash": 0.0,
        "units": 663.9224538573894
      },
      "hold_equity": 48.02815031204355,
      "price": 0.07234
    },
    "ETH/USD": {
      "agent": {
        "cash": 50.4269523544189,
        "sig": 0.0,
        "strategy": "ts_momentum",
        "units": 0.0
      },
      "agent_equity": 50.4269523544189,
      "hold": {
        "cash": 0.0,
        "units": 0.03149388073897242
      },
      "hold_equity": 49.763480955650316,
      "price": 1580.1
    },
    "GOOGL": {
      "agent": {
        "cash": 50.0,
        "sig": 0.0,
        "strategy": "rsi_reversion",
        "units": 0.0
      },
      "agent_equity": 50.0,
      "hold": {
        "cash": 0.0,
        "units": 0.1481964427788425
      },
      "hold_equity": 51.98433444926895,
      "price": 350.7799072265625
    },
    "LINK/USD": {
      "agent": {
        "cash": 0.0,
        "sig": 1.0,
        "strategy": "buy_and_hold",
        "units": 6.792555359326179
      },
      "agent_equity": 49.619616899877734,
      "hold": {
        "cash": 0.0,
        "units": 6.792555359326179
      },
      "hold_equity": 49.619616899877734,
      "price": 7.305
    },
    "LTC/USD": {
      "agent": {
        "cash": 50.0,
        "sig": 0.0,
        "strategy": "rsi_reversion",
        "units": 0.0
      },
      "agent_equity": 50.0,
      "hold": {
        "cash": 0.0,
        "units": 1.1698642957416938
      },
      "hold_equity": 49.75432849789424,
      "price": 42.53
    },
    "META": {
      "agent": {
        "cash": -0.05000000000000426,
        "sig": 1.0,
        "strategy": "buy_and_hold",
        "units": 0.08877840716668894
      },
      "agent_equity": 49.95,
      "hold": {
        "cash": 0.0,
        "units": 0.09086778736937756
      },
      "hold_equity": 51.17673895565936,
      "price": 563.2000122070312
    },
    "MSFT": {
      "agent": {
        "cash": 0.0,
        "sig": 1.0,
        "strategy": "buy_and_hold",
        "units": 0.13405903916227502
      },
      "agent_equity": 49.27741981515988,
      "hold": {
        "cash": 0.0,
        "units": 0.13405903916227502
      },
      "hold_equity": 49.27741981515988,
      "price": 367.5799865722656
    },
    "NVDA": {
      "agent": {
        "cash": 50.0,
        "sig": 0.0,
        "strategy": "sma_timing",
        "units": 0.0
      },
      "agent_equity": 50.0,
      "hold": {
        "cash": 0.0,
        "units": 0.2596997886927562
      },
      "hold_equity": 50.14021236607843,
      "price": 193.0699005126953
    },
    "QQQ": {
      "agent": {
        "cash": -7.105427357601002e-15,
        "sig": 1.0,
        "strategy": "buy_and_hold",
        "units": 0.07076940301447249
      },
      "agent_equity": 50.9766168977154,
      "hold": {
        "cash": 0.0,
        "units": 0.07076940301447249
      },
      "hold_equity": 50.97661689771541,
      "price": 720.3200073242188
    },
    "SOL/USD": {
      "agent": {
        "cash": 0.0,
        "sig": 1.0,
        "strategy": "buy_and_hold",
        "units": 0.6956037840845855
      },
      "agent_equity": 51.09905397885364,
      "hold": {
        "cash": 0.0,
        "units": 0.6956037840845855
      },
      "hold_equity": 51.09905397885364,
      "price": 73.46
    },
    "SPY": {
      "agent": {
        "cash": 0.0,
        "sig": 1.0,
        "strategy": "ts_momentum",
        "units": 0.06858804739407283
      },
      "agent_equity": 50.6419831189008,
      "hold": {
        "cash": 0.0,
        "units": 0.06858804739407283
      },
      "hold_equity": 50.6419831189008,
      "price": 738.3499755859375
    },
    "TSLA": {
      "agent": {
        "cash": 100.0,
        "sig": -1.0,
        "strategy": "macd",
        "units": -0.1316794425355944
      },
      "agent_equity": 46.90027685313458,
      "hold": {
        "cash": 0.0,
        "units": 0.1316794425355944
      },
      "hold_equity": 53.09972314686542,
      "price": 403.2499084472656
    },
    "XRP/USD": {
      "agent": {
        "cash": 0.0,
        "sig": 1.0,
        "strategy": "buy_and_hold",
        "units": 47.250047250047245
      },
      "agent_equity": 49.45662445662445,
      "hold": {
        "cash": 0.0,
        "units": 47.250047250047245
      },
      "hold_equity": 49.45662445662445,
      "price": 1.0467
    }
  },
  "created": "2026-06-27",
  "history": [
    {
      "agent_total": 900.0,
      "date": "2026-06-27",
      "hold_total": 900.0
    },
    {
      "agent_total": 900.0,
      "date": "2026-06-27",
      "hold_total": 900.0
    },
    {
      "agent_total": 898.5085747082028,
      "date": "2026-06-28",
      "hold_total": 895.3395369691184
    },
    {
      "agent_total": 894.9092255446823,
      "date": "2026-06-28",
      "hold_total": 889.7786061883053
    },
    {
      "agent_total": 898.4302273505317,
      "date": "2026-06-28",
      "hold_total": 895.1933624354183
    },
    {
      "agent_total": 900.4471955838201,
      "date": "2026-06-29",
      "hold_total": 906.1007685588108
    }
  ],
  "initial_capital": 900.0,
  "last_run": "2026-06-29",
  "symbols": [
    "BTC/USD",
    "ETH/USD",
    "SOL/USD",
    "XRP/USD",
    "DOGE/USD",
    "ADA/USD",
    "LTC/USD",
    "AVAX/USD",
    "LINK/USD",
    "AAPL",
    "MSFT",
    "NVDA",
    "TSLA",
    "AMZN",
    "GOOGL",
    "META",
    "SPY",
    "QQQ"
  ]
}